examples/html/flexbox_demo.html
examples/html/index.html
examples/html/new_features_demo.html
examples/html/page2.html
examples/html/showcase_complete.html
examples/html/svg_icons_demo.html
examples/html/svg_test.html
examples/html/themes_demo.html
mypygui_ng/__init__.py
mypygui_ng/__main__.py
mypygui_ng/demo.py
mypygui_ng/browser_window/__init__.py
mypygui_ng/core/__init__.py
mypygui_ng/core/exceptions.py
mypygui_ng/core/asynchronous/__init__.py
mypygui_ng/core/asynchronous/async_tools.py
mypygui_ng/core/asynchronous/decoraters.py
mypygui_ng/core/fs/__init__.py
mypygui_ng/core/fs/reading.py
mypygui_ng/core/fs/uri.py
mypygui_ng/core/services/__init__.py
mypygui_ng/core/services/service_provider.py
mypygui_ng/core/services/events/__init__.py
mypygui_ng/core/services/events/event.py
mypygui_ng/core/services/events/event_emitter.py
mypygui_ng/core/services/events/event_handler.py
mypygui_ng/core/services/layout_managing/__init__.py
mypygui_ng/core/services/layout_managing/layout_handler.py
mypygui_ng/core/services/rendering/__init__.py
mypygui_ng/core/services/rendering/composite.py
mypygui_ng/core/services/rendering/context.py
mypygui_ng/core/services/rendering/window_provider.py
mypygui_ng/core/services/resource_handling/__init__.py
mypygui_ng/core/services/resource_handling/resource_handler.py
mypygui_ng/core/services/worker/__init__.py
mypygui_ng/core/services/worker/worker.py
mypygui_ng/logging/__init__.py
mypygui_ng/logging/console.py
mypygui_ng/page/__init__.py
mypygui_ng/page/clipboard.py
mypygui_ng/page/page_globals.py
mypygui_ng/page/page_loader.py
mypygui_ng/page/page_loader_helper.py
mypygui_ng/page/py_component.py
mypygui_ng/page/css/__init__.py
mypygui_ng/page/css/literals.py
mypygui_ng/page/css/types.py
mypygui_ng/page/objects/__init__.py
mypygui_ng/page/objects/image_container.py
mypygui_ng/page/objects/cssom/__init__.py
mypygui_ng/page/objects/cssom/default_styles.py
mypygui_ng/page/objects/cssom/style_sheet.py
mypygui_ng/page/objects/dom/__init__.py
mypygui_ng-0.1.2.dist-info/licenses/LICENSE
mypygui_ng-0.1.2.dist-info/METADATA
mypygui_ng-0.1.2.dist-info/WHEEL
mypygui_ng-0.1.2.dist-info/entry_points.txt
mypygui_ng-0.1.2.dist-info/top_level.txt
mypygui_ng-0.1.2.dist-info/RECORD
