Metadata-Version: 2.4
Name: mypygui-ng
Version: 0.1.2
Summary: Modern GUIs for Python using HTML+CSS - A lightweight alternative to Electron
Home-page: https://github.com/Dragon-KK/mypygui
Author: Martin Alejandro Oviedo
Author-email: martin@oviedo.com.ar
License: MIT
Project-URL: Documentation, https://dragon-kk.github.io/mypygui/
Project-URL: Source, https://github.com/Dragon-KK/mypygui
Project-URL: Tracker, https://github.com/Dragon-KK/mypygui/issues
Keywords: gui,html,css,tkinter,web,interface,browser,rendering,mypygui,electron-alternative
Classifier: Development Status :: 4 - Beta
Classifier: Intended Audience :: Developers
Classifier: License :: OSI Approved :: MIT License
Classifier: Operating System :: OS Independent
Classifier: Programming Language :: Python :: 3
Classifier: Programming Language :: Python :: 3.10
Classifier: Programming Language :: Python :: 3.11
Classifier: Programming Language :: Python :: 3.12
Classifier: Topic :: Software Development :: User Interfaces
Classifier: Topic :: Multimedia :: Graphics
Classifier: Topic :: Internet :: WWW/HTTP :: Dynamic Content
Requires-Python: >=3.10
License-File: LICENSE
Requires-Dist: pillow>=9.1.0
Requires-Dist: tinycss2>=1.1.1
Requires-Dist: webcolors>=1.12
Requires-Dist: colorama>=0.4.4
Requires-Dist: requests>=2.28.1
Provides-Extra: demo
Requires-Dist: Pillow>=9.1.0; extra == "demo"
Provides-Extra: dev
Requires-Dist: pytest>=7.0.0; extra == "dev"
Requires-Dist: black>=23.0.0; extra == "dev"
Requires-Dist: flake8>=6.0.0; extra == "dev"
Dynamic: author
Dynamic: author-email
Dynamic: classifier
Dynamic: description
Dynamic: description-content-type
Dynamic: home-page
Dynamic: keywords
Dynamic: license
Dynamic: license-file
Dynamic: project-url
Dynamic: provides-extra
Dynamic: requires-dist
Dynamic: requires-python
Dynamic: summary
